[{"id":4876,"created_at":"2026-06-02T10:53:25Z","event":{"id":205805,"event_date":"2026-06-26T11:35:00Z","status":"notstarted","home_team_id":2040,"home_team":"Qingdao Hainiu","away_team_id":2039,"away_team":"Yunnan Yukun","league_id":52,"league_name":"Chinese Super League"},"markets":{"match_result":{"prob_home":31.0,"prob_draw":28.3,"prob_away":40.7,"predicted":"A"},"expected_goals":{"home":1.05,"away":0.93},"over_under":{"prob_over_15":74.0,"prob_over_25":51.2,"prob_over_35":31.0},"btts":{"prob_yes":65.2},"score":{"most_likely":"1-0"}},"recommendations":{"favorite":"A","favorite_prob":40.7,"bet_favorite":false,"over_15":false,"over_25":false,"over_35":false,"btts":false,"winner":false},"model":{"confidence":0.4074,"version":"v5.0"},"_pinnacle_odds":{},"_odds_snapshots":[]},{"id":4877,"created_at":"2026-06-02T10:53:25Z","event":{"id":8347,"event_date":"2026-06-26T19:00:00Z","status":"notstarted","home_team_id":488,"home_team":"Norway","away_team_id":485,"away_team":"France","league_id":27,"league_name":"World Cup 2026"},"markets":{"match_result":{"prob_home":42.0,"prob_draw":24.7,"prob_away":33.4,"predicted":"H"},"expected_goals":{"home":1.02,"away":1.35},"over_under":{"prob_over_15":75.3,"prob_over_25":44.2,"prob_over_35":19.0},"btts":{"prob_yes":48.2},"score":{"most_likely":"1-1"}},"recommendations":{"favorite":"H","favorite_prob":42.0,"bet_favorite":false,"over_15":false,"over_25":false,"over_35":false,"btts":false,"winner":false},"model":{"confidence":0.4196,"version":"v5.0"},"_pinnacle_odds":{},"_odds_snapshots":[]},{"id":4878,"created_at":"2026-06-02T10:53:25Z","event":{"id":8348,"event_date":"2026-06-26T19:00:00Z","status":"notstarted","home_team_id":486,"home_team":"Senegal","away_team_id":933,"away_team":"Iraq","league_id":27,"league_name":"World Cup 2026"},"markets":{"match_result":{"prob_home":44.3,"prob_draw":26.1,"prob_away":29.6,"predicted":"H"},"expected_goals":{"home":1.35,"away":1.4},"over_under":{"prob_over_15":70.1,"prob_over_25":36.8,"prob_over_35":23.8},"btts":{"prob_yes":45.7},"score":{"most_likely":"1-1"}},"recommendations":{"favorite":"H","favorite_prob":44.3,"bet_favorite":false,"over_15":false,"over_25":false,"over_35":false,"btts":false,"winner":false},"model":{"confidence":0.4434,"version":"v5.0"},"_pinnacle_odds":{},"_odds_snapshots":[]},{"id":4879,"created_at":"2026-06-02T10:53:26Z","event":{"id":10000,"event_date":"2026-06-26T22:00:00Z","status":"notstarted","home_team_id":836,"home_team":"Grêmio Novorizontino","away_team_id":826,"away_team":"Vila Nova FC","league_id":34,"league_name":"Brasileirão Serie B"},"markets":{"match_result":{"prob_home":39.2,"prob_draw":30.0,"prob_away":30.9,"predicted":"H"},"expected_goals":{"home":1.36,"away":0.91},"over_under":{"prob_over_15":69.0,"prob_over_25":41.3,"prob_over_35":18.0},"btts":{"prob_yes":51.7},"score":{"most_likely":"1-0"}},"recommendations":{"favorite":"H","favorite_prob":39.2,"bet_favorite":false,"over_15":false,"over_25":false,"over_35":false,"btts":false,"winner":false},"model":{"confidence":0.3917,"version":"v5.0"},"_pinnacle_odds":{},"_odds_snapshots":[]},{"id":5298,"created_at":"2026-06-22T02:20:10Z","event":{"id":210015,"event_date":"2026-06-26T09:30:00Z","status":"notstarted","home_team_id":3831,"home_team":"Rochedale Rovers","away_team_id":3108,"away_team":"Gold Coast Knights","league_id":70,"league_name":"NPL Queensland"},"markets":{"match_result":{"prob_home":28.8,"prob_draw":20.4,"prob_away":50.8,"predicted":"A"},"expected_goals":{"home":1.29,"away":1.65},"over_under":{"prob_over_15":83.6,"prob_over_25":60.8,"prob_over_35":44.1},"btts":{"prob_yes":67.3},"score":{"most_likely":"1-1"}},"recommendations":{"favorite":"A","favorite_prob":50.8,"bet_favorite":false,"over_15":false,"over_25":false,"over_35":false,"btts":false,"winner":false},"model":{"confidence":0.5083,"version":"v5.0"},"_pinnacle_odds":{}}]